robustprinter/__init__.py
robustprinter/printer.py
robustprinter/formatter/__init__.py
robustprinter/formatter/base.py
robustprinter/formatter/default.py
robustprinter-0.0.10.dist-info/LICENSE
robustprinter-0.0.10.dist-info/METADATA
robustprinter-0.0.10.dist-info/WHEEL
robustprinter-0.0.10.dist-info/top_level.txt
robustprinter-0.0.10.dist-info/RECORD
