Metadata-Version: 2.1
Name: robustprinter
Version: 0.0.10
Summary: Package for easy printing and logging to the terminal/console.
Home-page: https://github.com/stupidcucumber/RobustPrinter.git
Author: Ihor Kostiuk
Author-email: sk.companymail@gmail.com
License: MIT
Classifier: License :: OSI Approved :: MIT License
Classifier: Programming Language :: Python :: 3.10
Classifier: Operating System :: OS Independent
Requires-Python: >=3.10
License-File: LICENSE
Provides-Extra: dev
Requires-Dist: twine >=4.0.2 ; extra == 'dev'
